blockrs/__init__.py
blockrs/block.py
blockrs/utils.py
libblockrs/block.cpython-35m-darwin.so
libblockrs/block.cpython-36m-darwin.so
libblockrs/block.cpython-37m-darwin.so
blockrs-0.6.1.dist-info/LICENSE
blockrs-0.6.1.dist-info/METADATA
blockrs-0.6.1.dist-info/WHEEL
blockrs-0.6.1.dist-info/top_level.txt
blockrs-0.6.1.dist-info/RECORD
